selected_words_counter/FilterMinWords.py
selected_words_counter/__init__.py
selected_words_counter/counting.py
selected_words_counter/extract_files.py
selected_words_counter/selected_words_counter.py
selected_words_counter-0.7.dist-info/METADATA
selected_words_counter-0.7.dist-info/WHEEL
selected_words_counter-0.7.dist-info/top_level.txt
selected_words_counter-0.7.dist-info/RECORD
