Metadata-Version: 2.1
Name: selected_words_counter
Version: 0.7
Summary: A Python tool that counts specific selected words in a directory of files of different file formats. Outputs the results in a .excel file
Home-page: https://github.com/Provincie-Zuid-Holland/selected_words_counter
Author: Michael de Winter
Requires-Python: >=3.10
Requires-Dist: extract-msg
Requires-Dist: openpyxl ==3.1.5
Requires-Dist: pandas ==2.2.3
Requires-Dist: pypdf ==5.1.0
Requires-Dist: python-docx ==1.1.2
Requires-Dist: python-pptx ==0.6.23
Requires-Dist: tqdm >=4.66.3
Requires-Dist: xlrd ==2.0.1
Requires-Dist: pywin32 ==308 ; sys_platform == "win32"
